rascalrunner/__init__.py
rascalrunner/cli.py
rascalrunner/github_wrapper.py
rascalrunner/rascalrunner.py
rascalrunner/reconrunner.py
rascalrunner-0.2.0.dist-info/licenses/LICENSE
rascalrunner-0.2.0.dist-info/METADATA
rascalrunner-0.2.0.dist-info/WHEEL
rascalrunner-0.2.0.dist-info/entry_points.txt
rascalrunner-0.2.0.dist-info/top_level.txt
rascalrunner-0.2.0.dist-info/RECORD
