Metadata-Version: 2.4
Name: rascalrunner
Version: 0.2.0
Summary: A red team tool to leverage Github workflows and self-hosted runners
Home-page: https://github.com/nopcorn/rascalrunner
Author: nopcorn
Author-email: 
Classifier: Development Status :: 3 - Alpha
Classifier: Environment :: Console
Classifier: Intended Audience :: Developers
Classifier: Intended Audience :: System Administrators
Classifier: License :: OSI Approved :: MIT License
Classifier: Operating System :: OS Independent
Classifier: Programming Language :: Python :: 3
Classifier: Programming Language :: Python :: 3.7
Classifier: Programming Language :: Python :: 3.8
Classifier: Programming Language :: Python :: 3.9
Classifier: Programming Language :: Python :: 3.10
Classifier: Programming Language :: Python :: 3.11
Classifier: Topic :: Security
Classifier: Topic :: Software Development :: Testing
Requires-Python: >=3.7
License-File: LICENSE
Requires-Dist: GitPython==3.1.43
Requires-Dist: PyGithub==2.4.0
Requires-Dist: PyYAML==6.0.2
Requires-Dist: Requests==2.32.3
Requires-Dist: rich==13.9.4
Dynamic: author
Dynamic: classifier
Dynamic: description
Dynamic: description-content-type
Dynamic: home-page
Dynamic: license-file
Dynamic: requires-dist
Dynamic: requires-python
Dynamic: summary
